MPT5/Allimp.py
MPT5/Mainpro.py
MPT5/__init__.py
MPT5/__main__.py
MPT5/make.py
MPT5/requirements.txt
MPT5/update.py
MPT5/AI/Analiz.py
MPT5/AI/DBgen.py
MPT5/AI/Generats.py
MPT5/AI/OpnSrc.py
MPT5/AI/__init__.py
MPT5/AI/DL/TmpTest.py
MPT5/AI/DL/__init__.py
MPT5/AI/ML/ConMatrix.py
MPT5/AI/ML/DLPanel.py
MPT5/AI/ML/MLUtility.py
MPT5/AI/ML/SLPanel.py
MPT5/AI/ML/__init__.py
MPT5/AI/Test/AppTest.py
MPT5/AI/Test/__init__.py
MPT5/Config/Init.py
MPT5/Config/MLmethod.ini
MPT5/Config/__init__.py
MPT5/Config/option.ini
MPT5/Config/system1.ini
MPT5/DCC1/AuiPan2.py
MPT5/DCC1/DBDev2.py
MPT5/DCC1/ListPro2.py
MPT5/DCC1/MLDev2.py
MPT5/DCC1/MenuDev2.py
MPT5/DCC1/ProgDev2.py
MPT5/DCC1/Proper2.py
MPT5/DCC1/ToolBar2.py
MPT5/DCC1/__init__.py
MPT5/Database/Menu2.db
MPT5/Database/MenuSet2.py
MPT5/Database/PostGet.py
MPT5/Database/PostGet2.py
MPT5/Database/__init__.py
MPT5/Database/dbinterface.py
MPT5/Database/srcsql.py
MPT5/Database/wxsq.py
MPT5/Database/sqls/Createmenu.sql
MPT5/Database/sqls/__init__.py
MPT5/Fount/Allimp.py
MPT5/Fount/Createmenu.sql
MPT5/Fount/MLmethod.ini
MPT5/Fount/Mainpro.py
MPT5/Fount/__init__.py
MPT5/Fount/option.ini
MPT5/Fount/requirements.txt
MPT5/Fount/system1.ini
MPT5/Fount/update.py
MPT5/GUI/BG2.py
MPT5/GUI/MainMenu2.py
MPT5/GUI/MainTool.py
MPT5/GUI/Start.py
MPT5/GUI/__init__.py
MPT5/GUI/proman.py
MPT5/GUI/window2.py
MPT5/GUI/API/SamPnl.py
MPT5/GUI/API/SamPnl2.py
MPT5/GUI/API/__init__.py
MPT5/GUI/AuiPanel/PAui.py
MPT5/GUI/AuiPanel/__init__.py
MPT5/GUI/AuiPanel/tempane.py
MPT5/GUI/Main/DBv1.py
MPT5/GUI/Main/MDv1.py
MPT5/GUI/Main/MLv1.py
MPT5/GUI/Main/PAv1.py
MPT5/GUI/Main/PGv1.py
MPT5/GUI/Main/PPv1.py
MPT5/GUI/Main/TBv1.py
MPT5/GUI/Main/TPv1.py
MPT5/GUI/Main/__init__.py
MPT5/GUI/Temp/Demo.py
MPT5/GUI/Temp/Muntitle.py
MPT5/GUI/Temp/__init__.py
MPT5/GUI/Temp/untitle.py
MPT5/Locale/__init__.py
MPT5/Logs/__init__.py
MPT5/Res/Allicons.py
MPT5/Res/__init__.py
MPT5/Res/Fonts/__init__.py
MPT5/Res/Icons/__init__.py
MPT5/Res/Icons/16x16/__init__.py
MPT5.0.3.1-0.3.1.dist-info/LICENCE.txt
MPT5.0.3.1-0.3.1.dist-info/METADATA
MPT5.0.3.1-0.3.1.dist-info/WHEEL
MPT5.0.3.1-0.3.1.dist-info/top_level.txt
MPT5.0.3.1-0.3.1.dist-info/RECORD
