Metadata-Version: 2.1
Name: MPT5.0.3.1
Version: 0.3.1
Summary: ML PreLibrary Toolkit
Home-page: https://github.com/Srcfount/MPT5/
Author: Pooya Ghiami
Author-email: Pooya Ghiami <pooyagheyami@gmail.com>
License: GNU
Project-URL: Homepage, https://github.com/Srcfount/MPT5/
Project-URL: Bug Tracker, https://github.com/Srcfount/MPT5/issues
Keywords: MACHINELEARNING GUI SQL
Classifier: Programming Language :: Python :: 3
Classifier: Operating System :: OS Independent
Requires-Python: >=3.7
License-File: LICENCE.txt
Requires-Dist: wxPython
